{
  "formatVersion": 1,
  "database": {
    "version": 2,
    "identityHash": "14930952cee913f18751dd1acb7123f1",
    "entities": [
      {
        "tableName": "Note",
        "createSql": "CREATE TABLE IF NOT EXISTS `${TABLE_NAME}` (`noteId` INTEGER, `title` TEXT, `body` TEXT NOT NULL, `time` INTEGER NOT NULL, PRIMARY KEY(`noteId`))",
        "fields": [
          {
            "fieldPath": "noteId",
            "columnName": "noteId",
            "affinity": "INTEGER",
            "notNull": false
          },
          {
            "fieldPath": "title",
            "columnName": "title",
            "affinity": "TEXT",
            "notNull": false
          },
          {
            "fieldPath": "body",
            "columnName": "body",
            "affinity": "TEXT",
            "notNull": true
          },
          {
            "fieldPath": "time",
            "columnName": "time",
            "affinity": "INTEGER",
            "notNull": true
          }
        ],
        "primaryKey": {
          "autoGenerate": false,
          "columnNames": [
            "noteId"
          ]
        },
        "indices": [],
        "foreignKeys": []
      }
    ],
    "views": [],
    "setupQueries": [
      "CREATE TABLE IF NOT EXISTS room_master_table (id INTEGER PRIMARY KEY,identity_hash TEXT)",
      "INSERT OR REPLACE INTO room_master_table (id,identity_hash) VALUES(42, '14930952cee913f18751dd1acb7123f1')"
    ]
  }
}